vis_evaluator-0.0.3.dist-info/licenses/LICENSE
viseval/__init__.py
viseval/agent.py
viseval/dataset.py
viseval/evaluate.py
viseval/check/__init__.py
viseval/check/chart_check.py
viseval/check/data_check.py
viseval/check/deconstruct.py
viseval/check/layout_check.py
viseval/check/order_check.py
viseval/check/readability_check.py
viseval/check/scale_and_ticks_check.py
viseval/check/surface_form_check.py
viseval/check/time_utils.py
vis_evaluator-0.0.3.dist-info/METADATA
vis_evaluator-0.0.3.dist-info/WHEEL
vis_evaluator-0.0.3.dist-info/top_level.txt
vis_evaluator-0.0.3.dist-info/RECORD
