Metadata-Version: 2.4
Name: vis-evaluator
Version: 0.0.3
License: MIT
Project-URL: Documentation, https://github.com/microsoft/VisEval#readme
Project-URL: Issues, https://github.com/microsoft/VisEval/issues
Project-URL: Source, https://github.com/microsoft/VisEval
Requires-Python: >=3.10
License-File: LICENSE
Requires-Dist: langchain
Requires-Dist: python-dotenv
Requires-Dist: numpy
Requires-Dist: pandas
Requires-Dist: matplotlib
Requires-Dist: seaborn
Requires-Dist: CairoSVG
Requires-Dist: selenium
Requires-Dist: llmx
Provides-Extra: dev
Requires-Dist: pytest; extra == "dev"
Requires-Dist: flake8; extra == "dev"
Requires-Dist: pre-commit; extra == "dev"
Requires-Dist: black; extra == "dev"
Requires-Dist: isort; extra == "dev"
Requires-Dist: hatch; extra == "dev"
Requires-Dist: mlcopilot; extra == "dev"
Requires-Dist: lida; extra == "dev"
Dynamic: license-file
